LICENSE.txt
README.md
setup.cfg
setup.py
django_rtk/__init__.py
django_rtk/signals.py
django_rtk/validators.py
django_rtk.egg-info/PKG-INFO
django_rtk.egg-info/SOURCES.txt
django_rtk.egg-info/dependency_links.txt
django_rtk.egg-info/not-zip-safe
django_rtk.egg-info/requires.txt
django_rtk.egg-info/top_level.txt
django_rtk/mutations/__init__.py
django_rtk/mutations/activateaccount.py
django_rtk/mutations/changepassword.py
django_rtk/mutations/obtainjsonwebtoken.py
django_rtk/mutations/registeraccount.py
django_rtk/mutations/requestmagiclink.py
django_rtk/mutations/requestpasswordreset.py
django_rtk/mutations/resetpassword.py
django_rtk/mutations/signinbymagiclink.py
django_rtk/queries/__init__.py
django_rtk/queries/me.py
django_rtk/utils/__init__.py
django_rtk/utils/errors.py
django_rtk/utils/extract_token.py
django_rtk/utils/get_backend.py
django_rtk/utils/get_setting_or.py
django_rtk/utils/get_validator.py
django_rtk/utils/import_class.py
django_rtk/utils/send_email.py