Metadata-Version: 2.1
Name: django-rtk
Version: 0.4.0
Summary: Abstract basis for registrating Django users using graphql
Home-page: https://github.com/mnieber/django-rtk-home/blob/main/django-rtk/README.md
Author: Maarten Nieber
Author-email: hallomaarten@yahoo.com
License: MIT
Platform: UNKNOWN
Requires-Python: >=3.6
